colourconvert/__init__.py
colourconvert/colourconvert.py
colour_converter-0.0.5.dist-info/METADATA
colour_converter-0.0.5.dist-info/WHEEL
colour_converter-0.0.5.dist-info/top_level.txt
colour_converter-0.0.5.dist-info/RECORD
