Metadata-Version: 2.1
Name: colour-converter
Version: 0.0.5
Summary: converts different colour formats. 
Home-page: https://github.com/micfun123/colourconverpackage
Author: Michael Parker
Author-email: michaelrbparker@protonmail.com
License: UNKNOWN
Platform: UNKNOWN
